{
  "LoggerSettings": {
    "WriteToFile": true,
    "LogFilePath": "logs\\",
    "CompactConsoleLogging": false,
    "ElasticSearchUrl": null,
    "S3Bucket": null,
    "LogLevel": {
      "Default": "Information",
      "Microsoft": "Information",
      "Microsoft.AspNetCore": "Information",
      "Microsoft.Hosting.Lifetime": "Information",
      "Microsoft.AspNetCore.Authentication": "Information",
      "Microsoft.AspNetCore.Mvc.Infrastructure": "Information",
      "Microsoft.EntityFrameworkCore": "Information",
      "Microsoft.EntityFrameworkCore.Database.Command": "Warning"
    }
  }
}